passLastSemApex/__init__.py
passLastSemApex/ass1.txt
passLastSemApex/ass2.txt
passlastsemapex-0.1.1.dist-info/METADATA
passlastsemapex-0.1.1.dist-info/WHEEL
passlastsemapex-0.1.1.dist-info/top_level.txt
passlastsemapex-0.1.1.dist-info/RECORD
